{"skeleton":{"hash":"bR0ofjA5ldceMTkV8vgtAh28hXo","spine":"2.0.23","width":44,"height":68},"bones":[{"name":"root"}],"slots":[{"name":"diamond_idle_1_crop","bone":"root","attachment":"diamond_idle_1_crop"}],"skins":{"default":{"diamond_idle_1_crop":{"diamond_idle_1_crop":{"width":44,"height":68},"diamond_idle_2_crop":{"width":44,"height":68},"diamond_jump_crop":{"width":36,"height":68}}}},"animations":{"dash":{"bones":{"root":{"rotate":[{"time":0,"angle":0},{"time":0.1333,"angle":-42.11},{"time":0.3333,"angle":-62.25}]}}},"dodge":{"bones":{"root":{"rotate":[{"time":0,"angle":0},{"time":0.1333,"angle":33.43}]}}},"idle":{"slots":{"diamond_idle_1_crop":{"attachment":[{"time":0,"name":"diamond_idle_1_crop"},{"time":0.1666,"name":"diamond_idle_2_crop"},{"time":0.3333,"name":"diamond_idle_1_crop"}]}}},"jump":{"slots":{"diamond_idle_1_crop":{"attachment":[{"time":0.1,"name":"diamond_jump_crop"}]}}},"walk":{"bones":{"root":{"rotate":[{"time":0,"angle":0},{"time":0.2666,"angle":-29.72}]}}}}}